xia_mail/__init__.py
xia_mail/mail.cpython-311-darwin.so
xia_mail-0.1.4.dist-info/LICENSE.txt
xia_mail-0.1.4.dist-info/METADATA
xia_mail-0.1.4.dist-info/WHEEL
xia_mail-0.1.4.dist-info/top_level.txt
xia_mail-0.1.4.dist-info/RECORD
